exokheia/__init__.py
exokheia/exokheia.py
exokheia-0.1.0.dist-info/LICENSE
exokheia-0.1.0.dist-info/WHEEL
exokheia-0.1.0.dist-info/METADATA
exokheia-0.1.0.dist-info/RECORD
