Metadata-Version: 2.1
Name: exokheia
Version: 0.1.0
Summary: Abstraction layer for modeling sources of opinion
Home-page: https://github.com/datagazing/exokheia
Author: Brendan Strejcek
Author-email: brendan@datagazing.com
Requires-Python: >=3.7
Classifier: License :: OSI Approved :: MIT License
